{"total":6, "rows": [{
            "orderNumber":"1",
			"idName":"Z0769000000",
			"allName":"北方国际信托股份公司"
		},{
		    "orderNumber":"2",
			"idName":"A0009000084",
			"allName":"北京国际信托公司"
		},{
			"orderNumber":"3",
			"idName":"A0097000001",
			"allName":"长城证券"
		},{
			"orderNumber":"4",
			"idName":"000000002307",
			"allName":"重庆农商行"
		},{
			"orderNumber":"5",
			"idName":"A0021000001",
			"allName":"重庆银行"
		},{
			"orderNumber":"6",
			"idName":"A0055000001",
			"allName":"东莞银行"
		},{
		    "orderNumber":"7",
			"idName":"A0009000084",
			"allName":"北京国际信托公司"
		},{
			"orderNumber":"8",
			"idName":"A0097000001",
			"allName":"长城证券"
		},{
			"orderNumber":"9",
			"idName":"000000002307",
			"allName":"重庆农商行"
		},{
			"orderNumber":"10",
			"idName":"A0021000001",
			"allName":"重庆银行"
		},{
			"orderNumber":"11",
			"idName":"A0055000001",
			"allName":"东莞银行"
		},{
			"orderNumber":"12",
			"idName":"A0097000001",
			"allName":"长城证券"
		},{
			"orderNumber":"13",
			"idName":"000000002307",
			"allName":"重庆农商行"
		},{
			"orderNumber":"14",
			"idName":"A0021000001",
			"allName":"重庆银行"
		},{
			"orderNumber":"15",
			"idName":"A0055000001",
			"allName":"东莞银行"
		}]}
